zyf/__init__.py
zyf/color.py
zyf/file.py
zyf/remote_control.py
zyf/settings.py
zyf/timer.py
zyf/user_agent.py
zyf/crawler/__init__.py
zyf/crawler/image/__init__.py
zyf/crawler/image/netbian.py
zyf/crawler/image/netnr.py
zyf/crawler/policy/__init__.py
zyf/crawler/policy/goverment_policy.py
zyf/crawler/policy/lexis_policy.py
zyf/crawler/policy/pkulaw_policy.py
zyf/db/__init__.py
zyf-1.3.dist-info/LICENSE
zyf-1.3.dist-info/METADATA
zyf-1.3.dist-info/WHEEL
zyf-1.3.dist-info/top_level.txt
zyf-1.3.dist-info/RECORD
