Metadata-Version: 2.1
Name: zyf
Version: 1.3
Summary: 常用函数工具包
Author: zhangyafei
Author-email: zhangyafeii@foxmail.com
Classifier: Programming Language :: Python :: 3
Classifier: License :: OSI Approved :: MIT License
Classifier: Operating System :: OS Independent
Requires-Python: >=3.6
License-File: LICENSE
Requires-Dist: prettytable
Requires-Dist: pandas
Requires-Dist: lxml
Requires-Dist: requests
Requires-Dist: tqdm
Requires-Dist: paramiko
